canva_ti/__init__.py
canva_ti/api_client.py
canva_ti/api_response.py
canva_ti/configuration.py
canva_ti/exceptions.py
canva_ti/py.typed
canva_ti/rest.py
canva_ti/api/__init__.py
canva_ti/api/app_api.py
canva_ti/api/asset_api.py
canva_ti/api/autofill_api.py
canva_ti/api/brand_template_api.py
canva_ti/api/comment_api.py
canva_ti/api/connect_api.py
canva_ti/api/design_api.py
canva_ti/api/design_import_api.py
canva_ti/api/export_api.py
canva_ti/api/folder_api.py
canva_ti/api/oauth_api.py
canva_ti/api/user_api.py
canva_ti/models/__init__.py
canva_ti/models/accepted_suggestion_event_type.py
canva_ti/models/add_suggestion_content.py
canva_ti/models/approval_request_action.py
canva_ti/models/approval_response_action.py
canva_ti/models/asset.py
canva_ti/models/asset_summary.py
canva_ti/models/asset_type.py
canva_ti/models/asset_upload_error.py
canva_ti/models/asset_upload_error_code.py
canva_ti/models/asset_upload_job.py
canva_ti/models/asset_upload_metadata.py
canva_ti/models/asset_upload_status.py
canva_ti/models/autofill_error.py
canva_ti/models/autofill_error_code.py
canva_ti/models/boolean_data_table_cell.py
canva_ti/models/brand_template.py
canva_ti/models/chart_data_field.py
canva_ti/models/comment.py
canva_ti/models/comment_event.py
canva_ti/models/comment_event_type.py
canva_ti/models/comment_notification_content.py
canva_ti/models/comment_object.py
canva_ti/models/comment_object_input.py
canva_ti/models/comment_thread_type.py
canva_ti/models/create_asset_upload_job_response.py
canva_ti/models/create_comment_request.py
canva_ti/models/create_comment_response.py
canva_ti/models/create_design_autofill_job_request.py
canva_ti/models/create_design_autofill_job_response.py
canva_ti/models/create_design_autofill_job_result.py
canva_ti/models/create_design_export_job_request.py
canva_ti/models/create_design_export_job_response.py
canva_ti/models/create_design_import_job_response.py
canva_ti/models/create_design_request.py
canva_ti/models/create_design_response.py
canva_ti-0.0.1.dist-info/METADATA
canva_ti-0.0.1.dist-info/WHEEL
canva_ti-0.0.1.dist-info/top_level.txt
canva_ti-0.0.1.dist-info/RECORD
